
{"items":[{"name":"Quickie.Apis.Crud","href":"Quickie.Apis.Crud.html","topicHref":"Quickie.Apis.Crud.html","topicUid":"Quickie.Apis.Crud","type":"Namespace","items":[{"name":"CrudController<TViewModel, TRequestHandler, TIdType>","href":"Quickie.Apis.Crud.CrudController-3.html","topicHref":"Quickie.Apis.Crud.CrudController-3.html","topicUid":"Quickie.Apis.Crud.CrudController`3","type":"Class"},{"name":"CrudForCollectionController<TViewModel, TRequestHandler, TIdType>","href":"Quickie.Apis.Crud.CrudForCollectionController-3.html","topicHref":"Quickie.Apis.Crud.CrudForCollectionController-3.html","topicUid":"Quickie.Apis.Crud.CrudForCollectionController`3","type":"Class"}]},{"name":"Quickie.Apis.Editonly","href":"Quickie.Apis.Editonly.html","topicHref":"Quickie.Apis.Editonly.html","topicUid":"Quickie.Apis.Editonly","type":"Namespace","items":[{"name":"EditOnlyController<TViewModel, TRequestHandler, TIdType>","href":"Quickie.Apis.Editonly.EditOnlyController-3.html","topicHref":"Quickie.Apis.Editonly.EditOnlyController-3.html","topicUid":"Quickie.Apis.Editonly.EditOnlyController`3","type":"Class"}]},{"name":"Quickie.Apis.Readonly","href":"Quickie.Apis.Readonly.html","topicHref":"Quickie.Apis.Readonly.html","topicUid":"Quickie.Apis.Readonly","type":"Namespace","items":[{"name":"ReadOnlyCollectionController<TViewModel, TRequestHandler, TRequestForDataModel, TIdType>","href":"Quickie.Apis.Readonly.ReadOnlyCollectionController-4.html","topicHref":"Quickie.Apis.Readonly.ReadOnlyCollectionController-4.html","topicUid":"Quickie.Apis.Readonly.ReadOnlyCollectionController`4","type":"Class"},{"name":"ReadOnlyController<TViewModel, TRequestHandler, TIdType>","href":"Quickie.Apis.Readonly.ReadOnlyController-3.html","topicHref":"Quickie.Apis.Readonly.ReadOnlyController-3.html","topicUid":"Quickie.Apis.Readonly.ReadOnlyController`3","type":"Class"}]},{"name":"Quickie.Apis.Writeonly","href":"Quickie.Apis.Writeonly.html","topicHref":"Quickie.Apis.Writeonly.html","topicUid":"Quickie.Apis.Writeonly","type":"Namespace","items":[{"name":"WriteOnlyController<TViewModel, TRequestHandler>","href":"Quickie.Apis.Writeonly.WriteOnlyController-2.html","topicHref":"Quickie.Apis.Writeonly.WriteOnlyController-2.html","topicUid":"Quickie.Apis.Writeonly.WriteOnlyController`2","type":"Class"}]},{"name":"Quickie.Base","href":"Quickie.Base.html","topicHref":"Quickie.Base.html","topicUid":"Quickie.Base","type":"Namespace","items":[{"name":"QuickieBaseApi","href":"Quickie.Base.QuickieBaseApi.html","topicHref":"Quickie.Base.QuickieBaseApi.html","topicUid":"Quickie.Base.QuickieBaseApi","type":"Class"}]},{"name":"Quickie.Configuration","href":"Quickie.Configuration.html","topicHref":"Quickie.Configuration.html","topicUid":"Quickie.Configuration","type":"Namespace","items":[{"name":"DependencyResolver","href":"Quickie.Configuration.DependencyResolver.html","topicHref":"Quickie.Configuration.DependencyResolver.html","topicUid":"Quickie.Configuration.DependencyResolver","type":"Class"},{"name":"QuickieExtension","href":"Quickie.Configuration.QuickieExtension.html","topicHref":"Quickie.Configuration.QuickieExtension.html","topicUid":"Quickie.Configuration.QuickieExtension","type":"Class"},{"name":"QuickieOptions","href":"Quickie.Configuration.QuickieOptions.html","topicHref":"Quickie.Configuration.QuickieOptions.html","topicUid":"Quickie.Configuration.QuickieOptions","type":"Class"}]},{"name":"Quickie.Configuration.Idempotency","href":"Quickie.Configuration.Idempotency.html","topicHref":"Quickie.Configuration.Idempotency.html","topicUid":"Quickie.Configuration.Idempotency","type":"Namespace","items":[{"name":"IIdempotencyProvider","href":"Quickie.Configuration.Idempotency.IIdempotencyProvider.html","topicHref":"Quickie.Configuration.Idempotency.IIdempotencyProvider.html","topicUid":"Quickie.Configuration.Idempotency.IIdempotencyProvider","type":"Interface"},{"name":"IdempotencyBackgroundService","href":"Quickie.Configuration.Idempotency.IdempotencyBackgroundService.html","topicHref":"Quickie.Configuration.Idempotency.IdempotencyBackgroundService.html","topicUid":"Quickie.Configuration.Idempotency.IdempotencyBackgroundService","type":"Class"},{"name":"IdempotentConfiguration","href":"Quickie.Configuration.Idempotency.IdempotentConfiguration.html","topicHref":"Quickie.Configuration.Idempotency.IdempotentConfiguration.html","topicUid":"Quickie.Configuration.Idempotency.IdempotentConfiguration","type":"Class"}]},{"name":"Quickie.Configuration.Idempotency.DefaultProvider","href":"Quickie.Configuration.Idempotency.DefaultProvider.html","topicHref":"Quickie.Configuration.Idempotency.DefaultProvider.html","topicUid":"Quickie.Configuration.Idempotency.DefaultProvider","type":"Namespace","items":[{"name":"InMemoryIdempotencyProvider","href":"Quickie.Configuration.Idempotency.DefaultProvider.InMemoryIdempotencyProvider.html","topicHref":"Quickie.Configuration.Idempotency.DefaultProvider.InMemoryIdempotencyProvider.html","topicUid":"Quickie.Configuration.Idempotency.DefaultProvider.InMemoryIdempotencyProvider","type":"Class"}]},{"name":"Quickie.Configuration.Middleware","href":"Quickie.Configuration.Middleware.html","topicHref":"Quickie.Configuration.Middleware.html","topicUid":"Quickie.Configuration.Middleware","type":"Namespace","items":[{"name":"IdempotencyMiddleware","href":"Quickie.Configuration.Middleware.IdempotencyMiddleware.html","topicHref":"Quickie.Configuration.Middleware.IdempotencyMiddleware.html","topicUid":"Quickie.Configuration.Middleware.IdempotencyMiddleware","type":"Class"}]},{"name":"Quickie.Configuration.Options","href":"Quickie.Configuration.Options.html","topicHref":"Quickie.Configuration.Options.html","topicUid":"Quickie.Configuration.Options","type":"Namespace","items":[{"name":"GlobalQuickieConfigData","href":"Quickie.Configuration.Options.GlobalQuickieConfigData.html","topicHref":"Quickie.Configuration.Options.GlobalQuickieConfigData.html","topicUid":"Quickie.Configuration.Options.GlobalQuickieConfigData","type":"Class"},{"name":"RateLimitConfiguration","href":"Quickie.Configuration.Options.RateLimitConfiguration.html","topicHref":"Quickie.Configuration.Options.RateLimitConfiguration.html","topicUid":"Quickie.Configuration.Options.RateLimitConfiguration","type":"Class"}]},{"name":"Quickie.DataHandlers.Crud.Definition","href":"Quickie.DataHandlers.Crud.Definition.html","topicHref":"Quickie.DataHandlers.Crud.Definition.html","topicUid":"Quickie.DataHandlers.Crud.Definition","type":"Namespace","items":[{"name":"ICrudDataHandler<TEntity, TIdType>","href":"Quickie.DataHandlers.Crud.Definition.ICrudDataHandler-2.html","topicHref":"Quickie.DataHandlers.Crud.Definition.ICrudDataHandler-2.html","topicUid":"Quickie.DataHandlers.Crud.Definition.ICrudDataHandler`2","type":"Interface"},{"name":"ICrudForCollectionDataHandler<TEntity, TIdType>","href":"Quickie.DataHandlers.Crud.Definition.ICrudForCollectionDataHandler-2.html","topicHref":"Quickie.DataHandlers.Crud.Definition.ICrudForCollectionDataHandler-2.html","topicUid":"Quickie.DataHandlers.Crud.Definition.ICrudForCollectionDataHandler`2","type":"Interface"}]},{"name":"Quickie.DataHandlers.Crud.Implementation","href":"Quickie.DataHandlers.Crud.Implementation.html","topicHref":"Quickie.DataHandlers.Crud.Implementation.html","topicUid":"Quickie.DataHandlers.Crud.Implementation","type":"Namespace","items":[{"name":"CrudDataHandler<TEntity, TDbContext, TIdType>","href":"Quickie.DataHandlers.Crud.Implementation.CrudDataHandler-3.html","topicHref":"Quickie.DataHandlers.Crud.Implementation.CrudDataHandler-3.html","topicUid":"Quickie.DataHandlers.Crud.Implementation.CrudDataHandler`3","type":"Class"},{"name":"CrudForCollectionDataDataHandler<TEntity, TIdType, TDbContext>","href":"Quickie.DataHandlers.Crud.Implementation.CrudForCollectionDataDataHandler-3.html","topicHref":"Quickie.DataHandlers.Crud.Implementation.CrudForCollectionDataDataHandler-3.html","topicUid":"Quickie.DataHandlers.Crud.Implementation.CrudForCollectionDataDataHandler`3","type":"Class"}]},{"name":"Quickie.DataHandlers.Editonly.Definition","href":"Quickie.DataHandlers.Editonly.Definition.html","topicHref":"Quickie.DataHandlers.Editonly.Definition.html","topicUid":"Quickie.DataHandlers.Editonly.Definition","type":"Namespace","items":[{"name":"IEditOnlyDataHandler<TEntity, TIdType>","href":"Quickie.DataHandlers.Editonly.Definition.IEditOnlyDataHandler-2.html","topicHref":"Quickie.DataHandlers.Editonly.Definition.IEditOnlyDataHandler-2.html","topicUid":"Quickie.DataHandlers.Editonly.Definition.IEditOnlyDataHandler`2","type":"Interface"}]},{"name":"Quickie.DataHandlers.Editonly.Implementation","href":"Quickie.DataHandlers.Editonly.Implementation.html","topicHref":"Quickie.DataHandlers.Editonly.Implementation.html","topicUid":"Quickie.DataHandlers.Editonly.Implementation","type":"Namespace","items":[{"name":"EditOnlyDataHandler<TEntity, TIdType>","href":"Quickie.DataHandlers.Editonly.Implementation.EditOnlyDataHandler-2.html","topicHref":"Quickie.DataHandlers.Editonly.Implementation.EditOnlyDataHandler-2.html","topicUid":"Quickie.DataHandlers.Editonly.Implementation.EditOnlyDataHandler`2","type":"Class"}]},{"name":"Quickie.DataHandlers.Readonly.Definition","href":"Quickie.DataHandlers.Readonly.Definition.html","topicHref":"Quickie.DataHandlers.Readonly.Definition.html","topicUid":"Quickie.DataHandlers.Readonly.Definition","type":"Namespace","items":[{"name":"IReadOnlyCollectionDataHandler<TEntity, TIdType>","href":"Quickie.DataHandlers.Readonly.Definition.IReadOnlyCollectionDataHandler-2.html","topicHref":"Quickie.DataHandlers.Readonly.Definition.IReadOnlyCollectionDataHandler-2.html","topicUid":"Quickie.DataHandlers.Readonly.Definition.IReadOnlyCollectionDataHandler`2","type":"Interface"},{"name":"IReadOnlyDataHandler<TEntity, TIdType>","href":"Quickie.DataHandlers.Readonly.Definition.IReadOnlyDataHandler-2.html","topicHref":"Quickie.DataHandlers.Readonly.Definition.IReadOnlyDataHandler-2.html","topicUid":"Quickie.DataHandlers.Readonly.Definition.IReadOnlyDataHandler`2","type":"Interface"}]},{"name":"Quickie.DataHandlers.Readonly.Implementation","href":"Quickie.DataHandlers.Readonly.Implementation.html","topicHref":"Quickie.DataHandlers.Readonly.Implementation.html","topicUid":"Quickie.DataHandlers.Readonly.Implementation","type":"Namespace","items":[{"name":"ReadOnlyCollectionDataHandler<TEntity, TDbContext, TIdType>","href":"Quickie.DataHandlers.Readonly.Implementation.ReadOnlyCollectionDataHandler-3.html","topicHref":"Quickie.DataHandlers.Readonly.Implementation.ReadOnlyCollectionDataHandler-3.html","topicUid":"Quickie.DataHandlers.Readonly.Implementation.ReadOnlyCollectionDataHandler`3","type":"Class"},{"name":"ReadOnlyDataHandler<TEntity, TDbContext, TIdType>","href":"Quickie.DataHandlers.Readonly.Implementation.ReadOnlyDataHandler-3.html","topicHref":"Quickie.DataHandlers.Readonly.Implementation.ReadOnlyDataHandler-3.html","topicUid":"Quickie.DataHandlers.Readonly.Implementation.ReadOnlyDataHandler`3","type":"Class"}]},{"name":"Quickie.DataHandlers.Writeonly.Definition","href":"Quickie.DataHandlers.Writeonly.Definition.html","topicHref":"Quickie.DataHandlers.Writeonly.Definition.html","topicUid":"Quickie.DataHandlers.Writeonly.Definition","type":"Namespace","items":[{"name":"IWriteOnlyDataHandler<TEntity>","href":"Quickie.DataHandlers.Writeonly.Definition.IWriteOnlyDataHandler-1.html","topicHref":"Quickie.DataHandlers.Writeonly.Definition.IWriteOnlyDataHandler-1.html","topicUid":"Quickie.DataHandlers.Writeonly.Definition.IWriteOnlyDataHandler`1","type":"Interface"}]},{"name":"Quickie.DataHandlers.Writeonly.Implementation","href":"Quickie.DataHandlers.Writeonly.Implementation.html","topicHref":"Quickie.DataHandlers.Writeonly.Implementation.html","topicUid":"Quickie.DataHandlers.Writeonly.Implementation","type":"Namespace","items":[{"name":"WriteOnlyDataHandler<TEntity, TDbContext>","href":"Quickie.DataHandlers.Writeonly.Implementation.WriteOnlyDataHandler-2.html","topicHref":"Quickie.DataHandlers.Writeonly.Implementation.WriteOnlyDataHandler-2.html","topicUid":"Quickie.DataHandlers.Writeonly.Implementation.WriteOnlyDataHandler`2","type":"Class"}]},{"name":"Quickie.DataObj","href":"Quickie.DataObj.html","topicHref":"Quickie.DataObj.html","topicUid":"Quickie.DataObj","type":"Namespace","items":[{"name":"DetailedResponseObj","href":"Quickie.DataObj.DetailedResponseObj.html","topicHref":"Quickie.DataObj.DetailedResponseObj.html","topicUid":"Quickie.DataObj.DetailedResponseObj","type":"Class"},{"name":"PaginatedDataObj<TObject>","href":"Quickie.DataObj.PaginatedDataObj-1.html","topicHref":"Quickie.DataObj.PaginatedDataObj-1.html","topicUid":"Quickie.DataObj.PaginatedDataObj`1","type":"Class"},{"name":"RequestForDataObj","href":"Quickie.DataObj.RequestForDataObj.html","topicHref":"Quickie.DataObj.RequestForDataObj.html","topicUid":"Quickie.DataObj.RequestForDataObj","type":"Class"},{"name":"ResponseObj","href":"Quickie.DataObj.ResponseObj.html","topicHref":"Quickie.DataObj.ResponseObj.html","topicUid":"Quickie.DataObj.ResponseObj","type":"Class"},{"name":"ResponseObj<TData>","href":"Quickie.DataObj.ResponseObj-1.html","topicHref":"Quickie.DataObj.ResponseObj-1.html","topicUid":"Quickie.DataObj.ResponseObj`1","type":"Class"}]},{"name":"Quickie.Handlers.Crud.Definition","href":"Quickie.Handlers.Crud.Definition.html","topicHref":"Quickie.Handlers.Crud.Definition.html","topicUid":"Quickie.Handlers.Crud.Definition","type":"Namespace","items":[{"name":"ICrudForCollectionRequestHandler<TViewModel, TIdType>","href":"Quickie.Handlers.Crud.Definition.ICrudForCollectionRequestHandler-2.html","topicHref":"Quickie.Handlers.Crud.Definition.ICrudForCollectionRequestHandler-2.html","topicUid":"Quickie.Handlers.Crud.Definition.ICrudForCollectionRequestHandler`2","type":"Interface"},{"name":"ICrudRequestHandler<TViewModel, TIdType>","href":"Quickie.Handlers.Crud.Definition.ICrudRequestHandler-2.html","topicHref":"Quickie.Handlers.Crud.Definition.ICrudRequestHandler-2.html","topicUid":"Quickie.Handlers.Crud.Definition.ICrudRequestHandler`2","type":"Interface"}]},{"name":"Quickie.Handlers.Crud.Implementation","href":"Quickie.Handlers.Crud.Implementation.html","topicHref":"Quickie.Handlers.Crud.Implementation.html","topicUid":"Quickie.Handlers.Crud.Implementation","type":"Namespace","items":[{"name":"CrudForCollectionRequestHandler<TViewModel, TEntity, TDataHandler, TIdType>","href":"Quickie.Handlers.Crud.Implementation.CrudForCollectionRequestHandler-4.html","topicHref":"Quickie.Handlers.Crud.Implementation.CrudForCollectionRequestHandler-4.html","topicUid":"Quickie.Handlers.Crud.Implementation.CrudForCollectionRequestHandler`4","type":"Class"},{"name":"CrudRequestHandler<TViewModel, TEntity, TDataHandler, TIdType>","href":"Quickie.Handlers.Crud.Implementation.CrudRequestHandler-4.html","topicHref":"Quickie.Handlers.Crud.Implementation.CrudRequestHandler-4.html","topicUid":"Quickie.Handlers.Crud.Implementation.CrudRequestHandler`4","type":"Class"}]},{"name":"Quickie.Handlers.Editonly.Definition","href":"Quickie.Handlers.Editonly.Definition.html","topicHref":"Quickie.Handlers.Editonly.Definition.html","topicUid":"Quickie.Handlers.Editonly.Definition","type":"Namespace","items":[{"name":"IEditOnlyRequestHandler<TViewModel, TIdType>","href":"Quickie.Handlers.Editonly.Definition.IEditOnlyRequestHandler-2.html","topicHref":"Quickie.Handlers.Editonly.Definition.IEditOnlyRequestHandler-2.html","topicUid":"Quickie.Handlers.Editonly.Definition.IEditOnlyRequestHandler`2","type":"Interface"}]},{"name":"Quickie.Handlers.Editonly.Implementation","href":"Quickie.Handlers.Editonly.Implementation.html","topicHref":"Quickie.Handlers.Editonly.Implementation.html","topicUid":"Quickie.Handlers.Editonly.Implementation","type":"Namespace","items":[{"name":"EditOnlyRequestHandler<TViewModel, TEntity, TDataHandler, TIdType>","href":"Quickie.Handlers.Editonly.Implementation.EditOnlyRequestHandler-4.html","topicHref":"Quickie.Handlers.Editonly.Implementation.EditOnlyRequestHandler-4.html","topicUid":"Quickie.Handlers.Editonly.Implementation.EditOnlyRequestHandler`4","type":"Class"}]},{"name":"Quickie.Handlers.Readonly.Definition","href":"Quickie.Handlers.Readonly.Definition.html","topicHref":"Quickie.Handlers.Readonly.Definition.html","topicUid":"Quickie.Handlers.Readonly.Definition","type":"Namespace","items":[{"name":"IReadOnlyCollectionRequestHandler<TViewModel, TIdType>","href":"Quickie.Handlers.Readonly.Definition.IReadOnlyCollectionRequestHandler-2.html","topicHref":"Quickie.Handlers.Readonly.Definition.IReadOnlyCollectionRequestHandler-2.html","topicUid":"Quickie.Handlers.Readonly.Definition.IReadOnlyCollectionRequestHandler`2","type":"Interface"},{"name":"IReadOnlyRequestHandler<TViewModel, TIdType>","href":"Quickie.Handlers.Readonly.Definition.IReadOnlyRequestHandler-2.html","topicHref":"Quickie.Handlers.Readonly.Definition.IReadOnlyRequestHandler-2.html","topicUid":"Quickie.Handlers.Readonly.Definition.IReadOnlyRequestHandler`2","type":"Interface"}]},{"name":"Quickie.Handlers.Readonly.Implementation","href":"Quickie.Handlers.Readonly.Implementation.html","topicHref":"Quickie.Handlers.Readonly.Implementation.html","topicUid":"Quickie.Handlers.Readonly.Implementation","type":"Namespace","items":[{"name":"ReadOnlyCollectionRequestHandler<TViewModel, TEntity, TDataHandler, TIdType>","href":"Quickie.Handlers.Readonly.Implementation.ReadOnlyCollectionRequestHandler-4.html","topicHref":"Quickie.Handlers.Readonly.Implementation.ReadOnlyCollectionRequestHandler-4.html","topicUid":"Quickie.Handlers.Readonly.Implementation.ReadOnlyCollectionRequestHandler`4","type":"Class"},{"name":"ReadOnlyRequestHandler<TViewModel, TEntity, TDataHandler, TIdType>","href":"Quickie.Handlers.Readonly.Implementation.ReadOnlyRequestHandler-4.html","topicHref":"Quickie.Handlers.Readonly.Implementation.ReadOnlyRequestHandler-4.html","topicUid":"Quickie.Handlers.Readonly.Implementation.ReadOnlyRequestHandler`4","type":"Class"}]},{"name":"Quickie.Handlers.Writeonly.Definition","href":"Quickie.Handlers.Writeonly.Definition.html","topicHref":"Quickie.Handlers.Writeonly.Definition.html","topicUid":"Quickie.Handlers.Writeonly.Definition","type":"Namespace","items":[{"name":"IWriteOnlyRequestHandler<TViewModel>","href":"Quickie.Handlers.Writeonly.Definition.IWriteOnlyRequestHandler-1.html","topicHref":"Quickie.Handlers.Writeonly.Definition.IWriteOnlyRequestHandler-1.html","topicUid":"Quickie.Handlers.Writeonly.Definition.IWriteOnlyRequestHandler`1","type":"Interface"}]},{"name":"Quickie.Handlers.Writeonly.Implementation","href":"Quickie.Handlers.Writeonly.Implementation.html","topicHref":"Quickie.Handlers.Writeonly.Implementation.html","topicUid":"Quickie.Handlers.Writeonly.Implementation","type":"Namespace","items":[{"name":"WriteOnlyRequestHandler<TViewModel, TEntity, TDataHandler>","href":"Quickie.Handlers.Writeonly.Implementation.WriteOnlyRequestHandler-3.html","topicHref":"Quickie.Handlers.Writeonly.Implementation.WriteOnlyRequestHandler-3.html","topicUid":"Quickie.Handlers.Writeonly.Implementation.WriteOnlyRequestHandler`3","type":"Class"}]},{"name":"Quickie.MinimalApis.Crud","href":"Quickie.MinimalApis.Crud.html","topicHref":"Quickie.MinimalApis.Crud.html","topicUid":"Quickie.MinimalApis.Crud","type":"Namespace","items":[{"name":"CrudEndpoints","href":"Quickie.MinimalApis.Crud.CrudEndpoints.html","topicHref":"Quickie.MinimalApis.Crud.CrudEndpoints.html","topicUid":"Quickie.MinimalApis.Crud.CrudEndpoints","type":"Class"},{"name":"CrudForCollectionEndpoints","href":"Quickie.MinimalApis.Crud.CrudForCollectionEndpoints.html","topicHref":"Quickie.MinimalApis.Crud.CrudForCollectionEndpoints.html","topicUid":"Quickie.MinimalApis.Crud.CrudForCollectionEndpoints","type":"Class"}]},{"name":"Quickie.MinimalApis.EditOnly","href":"Quickie.MinimalApis.EditOnly.html","topicHref":"Quickie.MinimalApis.EditOnly.html","topicUid":"Quickie.MinimalApis.EditOnly","type":"Namespace","items":[{"name":"EditOnlyEndpoints","href":"Quickie.MinimalApis.EditOnly.EditOnlyEndpoints.html","topicHref":"Quickie.MinimalApis.EditOnly.EditOnlyEndpoints.html","topicUid":"Quickie.MinimalApis.EditOnly.EditOnlyEndpoints","type":"Class"}]},{"name":"Quickie.MinimalApis.ReadOnly","href":"Quickie.MinimalApis.ReadOnly.html","topicHref":"Quickie.MinimalApis.ReadOnly.html","topicUid":"Quickie.MinimalApis.ReadOnly","type":"Namespace","items":[{"name":"ReadOnlyCollectionEndpoints","href":"Quickie.MinimalApis.ReadOnly.ReadOnlyCollectionEndpoints.html","topicHref":"Quickie.MinimalApis.ReadOnly.ReadOnlyCollectionEndpoints.html","topicUid":"Quickie.MinimalApis.ReadOnly.ReadOnlyCollectionEndpoints","type":"Class"},{"name":"ReadOnlyEndpoints","href":"Quickie.MinimalApis.ReadOnly.ReadOnlyEndpoints.html","topicHref":"Quickie.MinimalApis.ReadOnly.ReadOnlyEndpoints.html","topicUid":"Quickie.MinimalApis.ReadOnly.ReadOnlyEndpoints","type":"Class"}]},{"name":"Quickie.MinimalApis.WriteOnly","href":"Quickie.MinimalApis.WriteOnly.html","topicHref":"Quickie.MinimalApis.WriteOnly.html","topicUid":"Quickie.MinimalApis.WriteOnly","type":"Namespace","items":[{"name":"WriteOnlyEndpoints","href":"Quickie.MinimalApis.WriteOnly.WriteOnlyEndpoints.html","topicHref":"Quickie.MinimalApis.WriteOnly.WriteOnlyEndpoints.html","topicUid":"Quickie.MinimalApis.WriteOnly.WriteOnlyEndpoints","type":"Class"}]},{"name":"Quickie.Types","href":"Quickie.Types.html","topicHref":"Quickie.Types.html","topicUid":"Quickie.Types","type":"Namespace","items":[{"name":"ErrorStatusEnum","href":"Quickie.Types.ErrorStatusEnum.html","topicHref":"Quickie.Types.ErrorStatusEnum.html","topicUid":"Quickie.Types.ErrorStatusEnum","type":"Enum"}]},{"name":"Quickie.Types.Crud","href":"Quickie.Types.Crud.html","topicHref":"Quickie.Types.Crud.html","topicUid":"Quickie.Types.Crud","type":"Namespace","items":[{"name":"CrudDto","href":"Quickie.Types.Crud.CrudDto.html","topicHref":"Quickie.Types.Crud.CrudDto.html","topicUid":"Quickie.Types.Crud.CrudDto","type":"Class"},{"name":"CrudEntity","href":"Quickie.Types.Crud.CrudEntity.html","topicHref":"Quickie.Types.Crud.CrudEntity.html","topicUid":"Quickie.Types.Crud.CrudEntity","type":"Class"}]},{"name":"Quickie.Types.Editonly","href":"Quickie.Types.Editonly.html","topicHref":"Quickie.Types.Editonly.html","topicUid":"Quickie.Types.Editonly","type":"Namespace","items":[{"name":"EditOnlyDto","href":"Quickie.Types.Editonly.EditOnlyDto.html","topicHref":"Quickie.Types.Editonly.EditOnlyDto.html","topicUid":"Quickie.Types.Editonly.EditOnlyDto","type":"Class"},{"name":"EditOnlyEntity","href":"Quickie.Types.Editonly.EditOnlyEntity.html","topicHref":"Quickie.Types.Editonly.EditOnlyEntity.html","topicUid":"Quickie.Types.Editonly.EditOnlyEntity","type":"Class"}]},{"name":"Quickie.Types.Readonly","href":"Quickie.Types.Readonly.html","topicHref":"Quickie.Types.Readonly.html","topicUid":"Quickie.Types.Readonly","type":"Namespace","items":[{"name":"ReadOnlyDto","href":"Quickie.Types.Readonly.ReadOnlyDto.html","topicHref":"Quickie.Types.Readonly.ReadOnlyDto.html","topicUid":"Quickie.Types.Readonly.ReadOnlyDto","type":"Class"},{"name":"ReadOnlyEntity","href":"Quickie.Types.Readonly.ReadOnlyEntity.html","topicHref":"Quickie.Types.Readonly.ReadOnlyEntity.html","topicUid":"Quickie.Types.Readonly.ReadOnlyEntity","type":"Class"}]},{"name":"Quickie.Types.Writable","href":"Quickie.Types.Writable.html","topicHref":"Quickie.Types.Writable.html","topicUid":"Quickie.Types.Writable","type":"Namespace","items":[{"name":"WriteOnlyDto","href":"Quickie.Types.Writable.WriteOnlyDto.html","topicHref":"Quickie.Types.Writable.WriteOnlyDto.html","topicUid":"Quickie.Types.Writable.WriteOnlyDto","type":"Class"},{"name":"WriteOnlyEntity","href":"Quickie.Types.Writable.WriteOnlyEntity.html","topicHref":"Quickie.Types.Writable.WriteOnlyEntity.html","topicUid":"Quickie.Types.Writable.WriteOnlyEntity","type":"Class"}]},{"name":"specification.Controllers","href":"specification.Controllers.html","topicHref":"specification.Controllers.html","topicUid":"specification.Controllers","type":"Namespace","items":[{"name":"CrudControllerTests","href":"specification.Controllers.CrudControllerTests.html","topicHref":"specification.Controllers.CrudControllerTests.html","topicUid":"specification.Controllers.CrudControllerTests","type":"Class"},{"name":"CrudForCollectionControllerTests","href":"specification.Controllers.CrudForCollectionControllerTests.html","topicHref":"specification.Controllers.CrudForCollectionControllerTests.html","topicUid":"specification.Controllers.CrudForCollectionControllerTests","type":"Class"},{"name":"EditOnlyControllerTests","href":"specification.Controllers.EditOnlyControllerTests.html","topicHref":"specification.Controllers.EditOnlyControllerTests.html","topicUid":"specification.Controllers.EditOnlyControllerTests","type":"Class"},{"name":"ReadOnlyCollectionControllerTests","href":"specification.Controllers.ReadOnlyCollectionControllerTests.html","topicHref":"specification.Controllers.ReadOnlyCollectionControllerTests.html","topicUid":"specification.Controllers.ReadOnlyCollectionControllerTests","type":"Class"},{"name":"ReadOnlyControllerTests","href":"specification.Controllers.ReadOnlyControllerTests.html","topicHref":"specification.Controllers.ReadOnlyControllerTests.html","topicUid":"specification.Controllers.ReadOnlyControllerTests","type":"Class"},{"name":"WriteOnlyControllerTests","href":"specification.Controllers.WriteOnlyControllerTests.html","topicHref":"specification.Controllers.WriteOnlyControllerTests.html","topicUid":"specification.Controllers.WriteOnlyControllerTests","type":"Class"}]},{"name":"specification.DataHandlers","href":"specification.DataHandlers.html","topicHref":"specification.DataHandlers.html","topicUid":"specification.DataHandlers","type":"Namespace","items":[{"name":"CrudDataHandlerTests","href":"specification.DataHandlers.CrudDataHandlerTests.html","topicHref":"specification.DataHandlers.CrudDataHandlerTests.html","topicUid":"specification.DataHandlers.CrudDataHandlerTests","type":"Class"},{"name":"EditOnlyDataHandlerTests","href":"specification.DataHandlers.EditOnlyDataHandlerTests.html","topicHref":"specification.DataHandlers.EditOnlyDataHandlerTests.html","topicUid":"specification.DataHandlers.EditOnlyDataHandlerTests","type":"Class"},{"name":"ReadOnlyCollectionDataHandlerTests","href":"specification.DataHandlers.ReadOnlyCollectionDataHandlerTests.html","topicHref":"specification.DataHandlers.ReadOnlyCollectionDataHandlerTests.html","topicUid":"specification.DataHandlers.ReadOnlyCollectionDataHandlerTests","type":"Class"},{"name":"ReadOnlyDataHandlerTests","href":"specification.DataHandlers.ReadOnlyDataHandlerTests.html","topicHref":"specification.DataHandlers.ReadOnlyDataHandlerTests.html","topicUid":"specification.DataHandlers.ReadOnlyDataHandlerTests","type":"Class"},{"name":"WriteOnlyDataHandlerTests","href":"specification.DataHandlers.WriteOnlyDataHandlerTests.html","topicHref":"specification.DataHandlers.WriteOnlyDataHandlerTests.html","topicUid":"specification.DataHandlers.WriteOnlyDataHandlerTests","type":"Class"}]},{"name":"specification.Helpers.DataHandlers","href":"specification.Helpers.DataHandlers.html","topicHref":"specification.Helpers.DataHandlers.html","topicUid":"specification.Helpers.DataHandlers","type":"Namespace","items":[{"name":"CrudDataHandlerConcrete","href":"specification.Helpers.DataHandlers.CrudDataHandlerConcrete.html","topicHref":"specification.Helpers.DataHandlers.CrudDataHandlerConcrete.html","topicUid":"specification.Helpers.DataHandlers.CrudDataHandlerConcrete","type":"Class"},{"name":"EditOnlyDataHandlerConcrete","href":"specification.Helpers.DataHandlers.EditOnlyDataHandlerConcrete.html","topicHref":"specification.Helpers.DataHandlers.EditOnlyDataHandlerConcrete.html","topicUid":"specification.Helpers.DataHandlers.EditOnlyDataHandlerConcrete","type":"Class"},{"name":"ReadOnlyCollectionDataHandlerConcrete","href":"specification.Helpers.DataHandlers.ReadOnlyCollectionDataHandlerConcrete.html","topicHref":"specification.Helpers.DataHandlers.ReadOnlyCollectionDataHandlerConcrete.html","topicUid":"specification.Helpers.DataHandlers.ReadOnlyCollectionDataHandlerConcrete","type":"Class"},{"name":"ReadOnlyDataHandlerConcrete","href":"specification.Helpers.DataHandlers.ReadOnlyDataHandlerConcrete.html","topicHref":"specification.Helpers.DataHandlers.ReadOnlyDataHandlerConcrete.html","topicUid":"specification.Helpers.DataHandlers.ReadOnlyDataHandlerConcrete","type":"Class"},{"name":"WriteOnlyDataHandlerConcrete","href":"specification.Helpers.DataHandlers.WriteOnlyDataHandlerConcrete.html","topicHref":"specification.Helpers.DataHandlers.WriteOnlyDataHandlerConcrete.html","topicUid":"specification.Helpers.DataHandlers.WriteOnlyDataHandlerConcrete","type":"Class"}]},{"name":"specification.Helpers.Dtos","href":"specification.Helpers.Dtos.html","topicHref":"specification.Helpers.Dtos.html","topicUid":"specification.Helpers.Dtos","type":"Namespace","items":[{"name":"CrudDtoConcrete","href":"specification.Helpers.Dtos.CrudDtoConcrete.html","topicHref":"specification.Helpers.Dtos.CrudDtoConcrete.html","topicUid":"specification.Helpers.Dtos.CrudDtoConcrete","type":"Class"},{"name":"EditOnlyDtoConcrete","href":"specification.Helpers.Dtos.EditOnlyDtoConcrete.html","topicHref":"specification.Helpers.Dtos.EditOnlyDtoConcrete.html","topicUid":"specification.Helpers.Dtos.EditOnlyDtoConcrete","type":"Class"},{"name":"FilterResult","href":"specification.Helpers.Dtos.FilterResult.html","topicHref":"specification.Helpers.Dtos.FilterResult.html","topicUid":"specification.Helpers.Dtos.FilterResult","type":"Class"},{"name":"ReadOnlyCollectionDataRequest","href":"specification.Helpers.Dtos.ReadOnlyCollectionDataRequest.html","topicHref":"specification.Helpers.Dtos.ReadOnlyCollectionDataRequest.html","topicUid":"specification.Helpers.Dtos.ReadOnlyCollectionDataRequest","type":"Class"},{"name":"ReadOnlyDtoConcrete","href":"specification.Helpers.Dtos.ReadOnlyDtoConcrete.html","topicHref":"specification.Helpers.Dtos.ReadOnlyDtoConcrete.html","topicUid":"specification.Helpers.Dtos.ReadOnlyDtoConcrete","type":"Class"},{"name":"WriteOnlyDtoConcrete","href":"specification.Helpers.Dtos.WriteOnlyDtoConcrete.html","topicHref":"specification.Helpers.Dtos.WriteOnlyDtoConcrete.html","topicUid":"specification.Helpers.Dtos.WriteOnlyDtoConcrete","type":"Class"}]},{"name":"specification.Helpers.Entities","href":"specification.Helpers.Entities.html","topicHref":"specification.Helpers.Entities.html","topicUid":"specification.Helpers.Entities","type":"Namespace","items":[{"name":"CrudEntityConcrete","href":"specification.Helpers.Entities.CrudEntityConcrete.html","topicHref":"specification.Helpers.Entities.CrudEntityConcrete.html","topicUid":"specification.Helpers.Entities.CrudEntityConcrete","type":"Class"},{"name":"EditOnlyEntityConcrete","href":"specification.Helpers.Entities.EditOnlyEntityConcrete.html","topicHref":"specification.Helpers.Entities.EditOnlyEntityConcrete.html","topicUid":"specification.Helpers.Entities.EditOnlyEntityConcrete","type":"Class"},{"name":"ReadOnlyEntityConcrete","href":"specification.Helpers.Entities.ReadOnlyEntityConcrete.html","topicHref":"specification.Helpers.Entities.ReadOnlyEntityConcrete.html","topicUid":"specification.Helpers.Entities.ReadOnlyEntityConcrete","type":"Class"},{"name":"WriteOnlyEntityConcrete","href":"specification.Helpers.Entities.WriteOnlyEntityConcrete.html","topicHref":"specification.Helpers.Entities.WriteOnlyEntityConcrete.html","topicUid":"specification.Helpers.Entities.WriteOnlyEntityConcrete","type":"Class"}]},{"name":"specification.Helpers.RequestHandlers","href":"specification.Helpers.RequestHandlers.html","topicHref":"specification.Helpers.RequestHandlers.html","topicUid":"specification.Helpers.RequestHandlers","type":"Namespace","items":[{"name":"CrudForCollectionRequestHandlerConcrete","href":"specification.Helpers.RequestHandlers.CrudForCollectionRequestHandlerConcrete.html","topicHref":"specification.Helpers.RequestHandlers.CrudForCollectionRequestHandlerConcrete.html","topicUid":"specification.Helpers.RequestHandlers.CrudForCollectionRequestHandlerConcrete","type":"Class"},{"name":"CrudRequestHandlerConcrete","href":"specification.Helpers.RequestHandlers.CrudRequestHandlerConcrete.html","topicHref":"specification.Helpers.RequestHandlers.CrudRequestHandlerConcrete.html","topicUid":"specification.Helpers.RequestHandlers.CrudRequestHandlerConcrete","type":"Class"},{"name":"EditOnlyRequestHandlerConcrete","href":"specification.Helpers.RequestHandlers.EditOnlyRequestHandlerConcrete.html","topicHref":"specification.Helpers.RequestHandlers.EditOnlyRequestHandlerConcrete.html","topicUid":"specification.Helpers.RequestHandlers.EditOnlyRequestHandlerConcrete","type":"Class"},{"name":"ReadOnlyCollectionRequestHandlerConcrete","href":"specification.Helpers.RequestHandlers.ReadOnlyCollectionRequestHandlerConcrete.html","topicHref":"specification.Helpers.RequestHandlers.ReadOnlyCollectionRequestHandlerConcrete.html","topicUid":"specification.Helpers.RequestHandlers.ReadOnlyCollectionRequestHandlerConcrete","type":"Class"},{"name":"ReadOnlyRequestHandlerConcrete","href":"specification.Helpers.RequestHandlers.ReadOnlyRequestHandlerConcrete.html","topicHref":"specification.Helpers.RequestHandlers.ReadOnlyRequestHandlerConcrete.html","topicUid":"specification.Helpers.RequestHandlers.ReadOnlyRequestHandlerConcrete","type":"Class"},{"name":"WriteOnlyRequestHandlerConcrete","href":"specification.Helpers.RequestHandlers.WriteOnlyRequestHandlerConcrete.html","topicHref":"specification.Helpers.RequestHandlers.WriteOnlyRequestHandlerConcrete.html","topicUid":"specification.Helpers.RequestHandlers.WriteOnlyRequestHandlerConcrete","type":"Class"}]},{"name":"specification.Helpers.TestsDbContext","href":"specification.Helpers.TestsDbContext.html","topicHref":"specification.Helpers.TestsDbContext.html","topicUid":"specification.Helpers.TestsDbContext","type":"Namespace","items":[{"name":"TestDbContext","href":"specification.Helpers.TestsDbContext.TestDbContext.html","topicHref":"specification.Helpers.TestsDbContext.TestDbContext.html","topicUid":"specification.Helpers.TestsDbContext.TestDbContext","type":"Class"}]},{"name":"specification.RequestHandlers","href":"specification.RequestHandlers.html","topicHref":"specification.RequestHandlers.html","topicUid":"specification.RequestHandlers","type":"Namespace","items":[{"name":"CrudForCollectionRequestHandlerTests","href":"specification.RequestHandlers.CrudForCollectionRequestHandlerTests.html","topicHref":"specification.RequestHandlers.CrudForCollectionRequestHandlerTests.html","topicUid":"specification.RequestHandlers.CrudForCollectionRequestHandlerTests","type":"Class"},{"name":"CrudRequestHandlerTests","href":"specification.RequestHandlers.CrudRequestHandlerTests.html","topicHref":"specification.RequestHandlers.CrudRequestHandlerTests.html","topicUid":"specification.RequestHandlers.CrudRequestHandlerTests","type":"Class"},{"name":"EditOnlyRequestHandlerTests","href":"specification.RequestHandlers.EditOnlyRequestHandlerTests.html","topicHref":"specification.RequestHandlers.EditOnlyRequestHandlerTests.html","topicUid":"specification.RequestHandlers.EditOnlyRequestHandlerTests","type":"Class"},{"name":"ReadOnlyCollectionRequestHandlerTests","href":"specification.RequestHandlers.ReadOnlyCollectionRequestHandlerTests.html","topicHref":"specification.RequestHandlers.ReadOnlyCollectionRequestHandlerTests.html","topicUid":"specification.RequestHandlers.ReadOnlyCollectionRequestHandlerTests","type":"Class"},{"name":"ReadOnlyRequestHandlerTests","href":"specification.RequestHandlers.ReadOnlyRequestHandlerTests.html","topicHref":"specification.RequestHandlers.ReadOnlyRequestHandlerTests.html","topicUid":"specification.RequestHandlers.ReadOnlyRequestHandlerTests","type":"Class"},{"name":"WriteOnlyRequestHandlerTests","href":"specification.RequestHandlers.WriteOnlyRequestHandlerTests.html","topicHref":"specification.RequestHandlers.WriteOnlyRequestHandlerTests.html","topicUid":"specification.RequestHandlers.WriteOnlyRequestHandlerTests","type":"Class"}]}],"memberLayout":"SamePage","pdf":true}
